pmxbot.rss-1.0.2-py3.7-nspkg.pth
pmxbot/rss.py
pmxbot.rss-1.0.2.dist-info/LICENSE
pmxbot.rss-1.0.2.dist-info/METADATA
pmxbot.rss-1.0.2.dist-info/WHEEL
pmxbot.rss-1.0.2.dist-info/entry_points.txt
pmxbot.rss-1.0.2.dist-info/namespace_packages.txt
pmxbot.rss-1.0.2.dist-info/top_level.txt
pmxbot.rss-1.0.2.dist-info/RECORD
