Metadata-Version: 2.1
Name: pmxbot.rss
Version: 1.0.2
Summary: RSS feed support for pmxbot
Home-page: https://github.com/yougov/pmxbot.rss
Author: YouGov, Plc.
Author-email: opensource@yougov.com
License: UNKNOWN
Platform: UNKNOWN
Classifier: Development Status :: 5 - Production/Stable
Classifier: Intended Audience :: Developers
Classifier: License :: OSI Approved :: MIT License
Classifier: Programming Language :: Python :: 3
Requires-Python: >=3.6
Requires-Dist: feedparser
Requires-Dist: tempora
Provides-Extra: docs
Requires-Dist: sphinx ; extra == 'docs'
Requires-Dist: jaraco.packaging (>=3.2) ; extra == 'docs'
Requires-Dist: rst.linker (>=1.9) ; extra == 'docs'
Provides-Extra: testing
Requires-Dist: pytest (!=3.7.3,>=3.5) ; extra == 'testing'
Requires-Dist: pytest-checkdocs ; extra == 'testing'
Requires-Dist: pytest-flake8 ; extra == 'testing'
Requires-Dist: jaraco.mongodb ; extra == 'testing'
Requires-Dist: pmxbot[irc] ; extra == 'testing'
